<?xml version="1.0"?>
<gameList>
	<game>
		<path>./audiosettings.rp</path>
		<name>Audio</name>
		<desc>Configure audio settings. Choose default of auto, 3.5mm jack, or HDMI. Mixer controls, and apply default settings.</desc>
		<image>/home/pi/RetroPie/retropiemenu/icons/audiosettings.png</image>
	</game>
	<game>
		<path>./bluetooth.rp</path>
		<name>Bluetooth</name>
		<desc>Register and connect to bluetooth devices. Unregister and remove devices, and display registered and connected devices.</desc>
		<image>/home/pi/RetroPie/retropiemenu/icons/bluetooth.png</image>
	</game>
	<game>
		<path>./configedit.rp</path>
		<name>Configuration Editor</name>
		<desc>Change common RetroArch options, and manually edit RetroArch configs, global configs, and non-RetroArch configs.</desc>
		<image>/home/pi/RetroPie/retropiemenu/icons/configedit.png</image>
	</game>
	<game>
		<path>./filemanager.rp</path>
		<name>File Manager</name>
		<desc>Basic ascii file manager for linux allowing you to browse, copy, delete, and move files.</desc>
		<image>/home/pi/RetroPie/retropiemenu/icons/filemanager.png</image>
	</game>
	<game>
		<path>./raspiconfig.rp</path>
		<name>Raspi-Config</name>
		<desc>Change user password, boot options, internationalization, camera, add your pi to Rastrack, overclock, overscan, memory split, SSH and more.</desc>
		<image>/home/pi/RetroPie/retropiemenu/icons/raspiconfig.png</image>
	</game>
	<game>
		<path>./retroarch.rp</path>
		<name>Retroarch</name>
		<desc>Launches the RetroArch GUI so you can change RetroArch options. Note: Changes will not be saved unless you have enabled the "Save Configuration On Exit" option.</desc>
		<image>/home/pi/RetroPie/retropiemenu/icons/retroarch.png</image>
	</game>
	<game>
		<path>./retronetplay.rp</path>
		<name>RetroArch Net Play</name>
		<desc>Set up RetroArch Netplay options, choose host or client, port, host IP, delay frames, and your nickname.</desc>
		<image>/home/pi/RetroPie/retropiemenu/icons/retronetplay.png</image>
	</game>
	<game>
		<path>./Bluetooth-Toggle/enable-bluetooth.sh</path>
		<name>enable-bluetooth</name>
		<desc>Enable bluetooth when needed</desc>
		<image>/home/pi/RetroPie/retropiemenu/icons/enable-bluetooth.png</image>
	</game>
	<game>
		<path>./Bluetooth-Toggle</path>
		<name>Bluetooth-Toggle</name>
		<desc>Toggle bluetooth on or off</desc>
		<image>/home/pi/RetroPie/retropiemenu/icons/Bluetooth-Toggle.png</image>
	</game>
	<game>
		<path>./WIFI-Toggle</path>
		<name>WiFi-Toggle</name>
		<desc>Toggle WIFI on or off</desc>
		<image>/home/pi/RetroPie/retropiemenu/icons/WIFI-Toggle.png</image>
	</game>
	<game>
		<path>./Bluetooth-Toggle/disable-bluetooth.sh</path>
		<name>disable-bluetooth</name>
		<desc>Disable bluetooth when not needed</desc>
		<image>./icons/disable-bluetooth.png</image>
		<playcount>1</playcount>
		<lastplayed>20190620T012528</lastplayed>
	</game>
	<game>
		<path>./control_updater_menu.sh</path>
		<name>control_updater_menu</name>
		<image>./icons/controllertools.png</image>
		<playcount>3</playcount>
		<lastplayed>20190726T202838</lastplayed>
	</game>
	<game>
		<path>./Controllertools/control_updater_menu.sh</path>
		<name>control_updater_menu</name>
		<image>./icons/controllertools.png</image>
		<playcount>3</playcount>
		<lastplayed>20190809T040420</lastplayed>
	</game>
	<game>
		<path>./esthemes.rp</path>
		<name>ES Themes</name>
		<desc>Install, uninstall, or update EmulationStation themes. Most themes can be previewed at https://github.com/retropie/ RetroPie-Setup/wiki/themes.</desc>
		<image>./icons/esthemes.png</image>
		<playcount>1</playcount>
		<lastplayed>20190912T163006</lastplayed>
	</game>
	<game>
		<path>./Kernel_Boot_Logo.sh</path>
		<name>Kernel boot logo installer</name>
		<desc>Kernel boot logo installer by Adam, switches between linux kernels with a different logo picture.</desc>
		<image>/home/pi/RetroPie/retropiemenu/icons/kernel-boot.png</image>
		<playcount>3</playcount>
		<lastplayed>20190809T040420</lastplayed>
	</game>
	<game>
		<path>./WIFI-Toggle/disable-WIFI.sh</path>
		<name>disable-WIFI</name>
		<desc>Disable WiFi when not needed</desc>
		<image>./icons/disable-WIFI.png</image>
		<playcount>1</playcount>
		<lastplayed>20190917T061208</lastplayed>
	</game>
	<game>
		<path>./WIFI-Toggle/enable-WIFI.sh</path>
		<name>enable-WIFI</name>
		<desc>Enable WiFi when needed</desc>
		<image>./icons/enable-WIFI.png</image>
		<playcount>1</playcount>
		<lastplayed>20190917T061901</lastplayed>
	</game>
	<game>
		<path>./wifi.rp</path>
		<name>WiFi</name>
		<desc>Connect to or disconnect from a wifi network and configure wifi settings.</desc>
		<image>./icons/wifi.png</image>
		<playcount>2</playcount>
		<lastplayed>20190917T062132</lastplayed>
	</game>
	<game>
		<path>./runcommand.rp</path>
		<name>Run Command Configuration</name>
		<desc>Change what appears on the runcommand screen. Enable or disable the menu, enable or disable box art, and change CPU configuration.</desc>
		<image>./icons/runcommand.png</image>
		<playcount>1</playcount>
		<lastplayed>20190920T091920</lastplayed>
	</game>
	<game>
		<path>./escollections.sh</path>
		<name>escollections</name>
		<playcount>1</playcount>
		<lastplayed>20190920T172015</lastplayed>
	</game>
	<game>
		<path>./splashscreen.rp</path>
		<name>Splash Screens</name>
		<desc>Enable or disable the splashscreen on RetroPie boot. Choose a splashscreen, download new splashscreens, and return splashscreen to default.</desc>
		<image>./icons/splashscreen.png</image>
		<playcount>10</playcount>
		<lastplayed>20190922T095402</lastplayed>
	</game>
	<game>
		<path>./showip.rp</path>
		<name>Show IP</name>
		<desc>Displays your current IP address, as well as other information provided by the command, "ip addr show."</desc>
		<image>./icons/showip.png</image>
		<playcount>9</playcount>
		<lastplayed>20190923T092346</lastplayed>
	</game>
	<game>
		<path>./rpsetup.rp</path>
		<name>RetroPie Setup</name>
		<desc>Install RetroPie from binary or source, install experimental packages, additional drivers, edit samba shares, custom scraper, as well as other RetroPie-related configurations.</desc>
		<image>./icons/rpsetup.png</image>
		<playcount>18</playcount>
		<lastplayed>20190926T142657</lastplayed>
	</game>
	<game>
		<path>./L4Menu</path>
		<name>L4 Menu</name>
		<desc>L4 Menu for advanced configuration.</desc>
		<image>./icons/L4.png</image>
		<playcount>0</playcount>
		<lastplayed>20190928T144320</lastplayed>
	</game>
</gameList>
